{
    "fullName" : "Subaru Impreza STI",
    "engine" : "2.5L I4 turbo",
    "image" : "http://www.zastavki.com/pictures/1920x1200/2010/Auto_Subaru_Subaru_Impreza_WRX_STI_a-line_Type_S_024075_.jpg",
    "bhp" : "305",
    "topSpeed" : "256",
    "drivetrain" : "AWD",
    "desc" : "Există o mulţime de variaţii disponibile ale pasajelor Lorem Ipsum, dar majoritatea lor au suferit alterări într-o oarecare măsură prin infiltrare de elemente de umor, sau de cuvinte luate aleator, care nu sunt câtuşi de puţin credibile. Daca vreţi să folosiţi un pasaj de Lorem Ipsum, trebuie să vă asiguraţi că nu conţine nimic stânjenitor ascuns printre randuri. Toate generatoarele de Lorem Ipsum de pe Internet tind să repete bucăţi de text în funcţie de necesitate, astfel făcându-l pe acesta primul generator adevarat de pe Internet."
} 